xaeian/__init__.py
xaeian/cbash.py
xaeian/colors.py
xaeian/crc.py
xaeian/cstruct.py
xaeian/files.py
xaeian/files_async.py
xaeian/log.py
xaeian/serial_port.py
xaeian/xstring.py
xaeian/xtime.py
xaeian/db/__init__.py
xaeian/db/abstract.py
xaeian/db/abstract_async.py
xaeian/db/errors.py
xaeian/db/mysql.py
xaeian/db/mysql_async.py
xaeian/db/postgres.py
xaeian/db/postgres_async.py
xaeian/db/sqlite.py
xaeian/db/sqlite_async.py
xaeian/db/utils.py
xaeian-0.1.0.dist-info/METADATA
xaeian-0.1.0.dist-info/WHEEL
xaeian-0.1.0.dist-info/top_level.txt
xaeian-0.1.0.dist-info/RECORD
