Metadata-Version: 2.4
Name: xaeian
Version: 0.1.0
Summary: Python utilities for files, strings, time, serial, structs, and database
Author: Xaeian
License: MIT
Project-URL: Repository, https://github.com/Xaeian/Python
Keywords: utilities,files,database,serial,crc,struct
Requires-Python: >=3.10
Provides-Extra: db
Requires-Dist: psycopg2-binary; extra == "db"
Requires-Dist: pymysql; extra == "db"
Provides-Extra: db-async
Requires-Dist: aiomysql; extra == "db-async"
Requires-Dist: aiosqlite; extra == "db-async"
Requires-Dist: asyncpg; extra == "db-async"
Provides-Extra: serial
Requires-Dist: pyserial; extra == "serial"
Provides-Extra: time
Requires-Dist: pytz; extra == "time"
Requires-Dist: tzlocal; extra == "time"
Provides-Extra: all
Requires-Dist: aiomysql; extra == "all"
Requires-Dist: aiosqlite; extra == "all"
Requires-Dist: asyncpg; extra == "all"
Requires-Dist: psycopg2-binary; extra == "all"
Requires-Dist: pymysql; extra == "all"
Requires-Dist: pyserial; extra == "all"
Requires-Dist: pytz; extra == "all"
Requires-Dist: tzlocal; extra == "all"
